yz_dubbo/__init__.py
yz_dubbo/client.py
yz_dubbo/config.py
yz_dubbo/exceptions.py
yz_dubbo-0.1.4.dist-info/METADATA
yz_dubbo-0.1.4.dist-info/WHEEL
yz_dubbo-0.1.4.dist-info/top_level.txt
yz_dubbo-0.1.4.dist-info/RECORD
